CHANGES.rst
MANIFEST.in
README.rst
django_orm_magic.py
setup.py
django_orm_magic.egg-info/PKG-INFO
django_orm_magic.egg-info/SOURCES.txt
django_orm_magic.egg-info/dependency_links.txt
django_orm_magic.egg-info/pbr.json
django_orm_magic.egg-info/requires.txt
django_orm_magic.egg-info/top_level.txt