Metadata-Version: 1.1
Name: django-orm-magic
Version: 0.4
Summary: An extension for IPython that help to define django's models in your interactive session.
Home-page: https://github.com/mgaitan/django-orm-magic
Author: Martin Gaitan
Author-email: gaitan@gmail.com
License: BSD
Keywords: ipython notebook django orm standalone
Platform: UNKNOWN
Classifier: Development Status :: 4 - Beta
Classifier: Environment :: Web Environment
Classifier: Framework :: IPython
Classifier: Framework :: Django
Classifier: License :: OSI Approved :: BSD License
Classifier: Operating System :: OS Independent
Classifier: Programming Language :: Python
Classifier: Topic :: Database
Classifier: Topic :: Scientific/Engineering :: Information Analysis
